__init__.py
main.py
modules/web/OpenAI/OpenAI.py
AIFunction_nekumelon-0.0.2.dist-info/METADATA
AIFunction_nekumelon-0.0.2.dist-info/WHEEL
AIFunction_nekumelon-0.0.2.dist-info/top_level.txt
AIFunction_nekumelon-0.0.2.dist-info/RECORD
