Metadata-Version: 2.1
Name: AIFunction-nekumelon
Version: 0.0.2
Summary: Generate realtime AI Functions!
Author-email: nekumelon <nekumelon@gmail.com>
Project-URL: Homepage, https://github.com/nekumelon/AIFunction
Classifier: Programming Language :: Python :: 3
Classifier: License :: OSI Approved :: MIT License
Classifier: Operating System :: OS Independent
Requires-Python: >=3.7
